{
    "chain_name": "crossfi",
    "registry_name": "crossfi",
    "api": [
        {"provider": "DashNode", "address": "https://crossfi-testnet-api.dashnode.org/"}
    ],
    "rpc": [
        {"provider": "DashNode", "address": "https://crossfi-testnet-rpc.dashnode.org/"}
    ],
    "sdk_version": "0.45.1",
    "coin_type": "60",
    "min_tx_fee": "800",
    "addr_prefix": "mx",
    "logo": "https://dashnode.org/assets/images/crypto-logo/crossfi.png",
    "assets": [{
        "base": "mpx",
        "symbol": "MPX",
        "exponent": "18",
        "coingecko_id": "unknown", 
        "logo": "https://dashnode.org/assets/images/crypto-logo/crossfi.png"
    }]
}
